TagHunter/__init__.py
TagHunter/aggregator.py
TagHunter/extractor.py
TagHunter/processor.py
TagHunter/updater.py
TagHunter/validator.py
TagHunter-1.0.0.dist-info/METADATA
TagHunter-1.0.0.dist-info/WHEEL
TagHunter-1.0.0.dist-info/top_level.txt
TagHunter-1.0.0.dist-info/RECORD
